Metadata-Version: 1.1
Name: kamabayEncoder
Version: 0.1.0
Summary: decode encode data.
Home-page: https://github.com/ExsoKamabay/EncoderDecoder
Author: Exso Kamabay
Author-email: UNKNOWN
License: Apache License 2.0
Keywords: kamabay,encode,decode,encrypt,decrypt
Platform: UNKNOWN
Classifier: License :: OSI Approved :: Apache Software License
Classifier: Operating System :: OS Independent
Classifier: Programming Language :: Python :: 3
Classifier: Topic :: Utilities
